Workbook
Name Patrimonio: INVESTIMENTO!$D$14
Name Rendimento_Carteira: INVESTIMENTO!$D$7
Name Salario: INVESTIMENTO!$D$6

Sheet Perguntas
A1: INVESTIMENTOS MENSAIS
A2: Quanto investir por mês?
A3: Por quanto tempo?
A4: Taxa de rendimento mensal?
A5: Patrimônio acumulado?
A6: Dividendos mensais?

Sheet INVESTIMENTO
B1: SCARPA INVEST
B5: CONFIGURAÇÕES
B6: Salário | D6: 2000
B7: Rendimento da carteira | D7: 0.006
B8: Sugestão de investimento | D8: =D6*30% -> 600
B10: INVESTIMENTOS MENSAIS
B11: Quanto investir por mês? | D11: 200
B12: Por quanto tempo? | D12: 5
B13: Taxa de rendimento mensal? | D13: 0.01079
B14: Patrimônio acumulado? | D14: =FV(D13,D12*12,-D11) -> 16755.383
B15: Dividendos mensais? | D15: =D14*Rendimento_Carteira -> 100.5323
B17: CENÁRIOS | D17: DIVIDENDOS
A19: 2 | B19: Quanto em 2 anos? | C19: =FV($D$13,A19*12,-$D$11) -> 5445.5255 | D19: =C19*Rendimento_Carteira -> 32.673153
A20: 5 | B20: Quanto em 5 anos? | C20: =FV($D$13,A20*12,-$D$11) -> 16755.383 | D20: =C20*Rendimento_Carteira -> 100.5323
A21: 10 | B21: Quanto em 10 anos? | C21: =FV($D$13,A21*12,-$D$11) -> 48656.843 | D21: =C21*Rendimento_Carteira -> 291.94106
A22: 20 | B22: Quanto em 20 anos? | C22: =FV($D$13,A22*12,-$D$11) -> 225039.68 | D22: =C22*Rendimento_Carteira -> 1350.2381
A23: 30 | B23: Quanto em 30 anos? | C23: =FV($D$13,A23*12,-$D$11) -> 864433.93 | D23: =C23*Rendimento_Carteira -> 5186.6036
B26: Perfil | D26: MODERADO
B27: Valor a ser investido mensal | D27: =$D$11 -> 200
B29: TIPO DE FII | C29: Percentual | D29: Valores
B30: PAPEL | C30: =VLOOKUP(($D$26&"-"&B30),apoio!$A$2:$D$19,4,0) -> 0.32 | D30: =C30*$D$27 -> 64
B31: TIJOLO | C31: =VLOOKUP(($D$26&"-"&B31),apoio!$A$2:$D$19,4,0) -> 0.4 | D31: =C31*$D$27 -> 80
B32: HÍBRIDOS | C32: =VLOOKUP(($D$26&"-"&B32),apoio!$A$2:$D$19,4,0) -> 0.08 | D32: =C32*$D$27 -> 16
B33: FOFs | C33: =VLOOKUP(($D$26&"-"&B33),apoio!$A$2:$D$19,4,0) -> 0.1 | D33: =C33*$D$27 -> 20
B34: DESENVOLVIMENTO | C34: =VLOOKUP(($D$26&"-"&B34),apoio!$A$2:$D$19,4,0) -> 0.1 | D34: =C34*$D$27 -> 20
B35: HOTELARIAS | C35: =VLOOKUP(($D$26&"-"&B35),apoio!$A$2:$D$19,4,0) -> 0 | D35: =C35*$D$27 -> 0
D36: =SUM(D30:D35) -> 200

Sheet apoio
A1: CHVE | B1: TIPO DE FII | C1: PERFIL | D1: % | J1: PERFIL
A2: =C2&"-"&B2 -> CONSERVADOR-PAPEL | B2: PAPEL | C2: CONSERVADOR | D2: 0.3 | J2: CONSERVADOR
A3: =C3&"-"&B3 -> CONSERVADOR-TIJOLO | B3: TIJOLO | C3: CONSERVADOR | D3: 0.5 | J3: MODERADO
A4: =C4&"-"&B4 -> CONSERVADOR-HÍBRIDOS | B4: HÍBRIDOS | C4: CONSERVADOR | D4: 0.1 | H4: % | J4: AGRESSIVO
A5: =C5&"-"&B5 -> CONSERVADOR-FOFs | B5: FOFs | C5: CONSERVADOR | D5: 0.1 | G5: CONSERVADOR-PAPEL | H5: =VLOOKUP(G5,A2:D19,4,0) -> 0.3
A6: =C6&"-"&B6 -> CONSERVADOR-DESENVOLVIMENTO | B6: DESENVOLVIMENTO | C6: CONSERVADOR | D6: 0
A7: =C7&"-"&B7 -> CONSERVADOR-HOTELARIAS | B7: HOTELARIAS | C7: CONSERVADOR | D7: 0
A8: =C8&"-"&B8 -> MODERADO-PAPEL | B8: PAPEL | C8: MODERADO | D8: 0.32
A9: =C9&"-"&B9 -> MODERADO-TIJOLO | B9: TIJOLO | C9: MODERADO | D9: 0.4
A10: =C10&"-"&B10 -> MODERADO-HÍBRIDOS | B10: HÍBRIDOS | C10: MODERADO | D10: 0.08
A11: =C11&"-"&B11 -> MODERADO-FOFs | B11: FOFs | C11: MODERADO | D11: 0.1
A12: =C12&"-"&B12 -> MODERADO-DESENVOLVIMENTO | B12: DESENVOLVIMENTO | C12: MODERADO | D12: 0.1
A13: =C13&"-"&B13 -> MODERADO-HOTELARIAS | B13: HOTELARIAS | C13: MODERADO | D13: 0
A14: =C14&"-"&B14 -> AGRESSIVO-PAPEL | B14: PAPEL | C14: AGRESSIVO | D14: 0.5
A15: =C15&"-"&B15 -> AGRESSIVO-TIJOLO | B15: TIJOLO | C15: AGRESSIVO | D15: 0.1
A16: =C16&"-"&B16 -> AGRESSIVO-HÍBRIDOS | B16: HÍBRIDOS | C16: AGRESSIVO | D16: 0.05
A17: =C17&"-"&B17 -> AGRESSIVO-FOFs | B17: FOFs | C17: AGRESSIVO | D17: 0.05
... A19: =C19&"-"&B19 -> AGRESSIVO-HOTELARIAS | B19: HOTELARIAS | C19: AGRESSIVO | D19: 0.1
